VendingMachine.v
module vending_machine_dual_mode (
    input wire clk,
    input wire reset,
    input wire [2:0] coin,        // 001=₹5, 010=₹10, 011=₹50, 100=₹100, 101=₹500
    input wire buy,               // Buy request
    input wire refund,            // Refund request
    input wire mode_select,       // 0 = Manual mode, 1 = Auto-bulk mode
    output reg product,           // Product dispense signal
    output reg refund_signal,     // Refund processed signal
    output reg [15:0] balance,    // Current balance
    output reg [15:0] change      // Returned change after auto-buy/refund
);

    // FSM states using parameter instead of typedef enum
    parameter IDLE     = 2'b00;
    parameter COLLECT  = 2'b01;
    parameter DISPENSE = 2'b10;
    parameter REFUND   = 2'b11;

    reg [1:0] current_state, next_state;

    // Coin decoder function
    function [15:0] coin_value;
        input [2:0] c;
        begin
            case (c)
                3'b001: coin_value = 5;
                3'b010: coin_value = 10;
                3'b011: coin_value = 50;
                3'b100: coin_value = 100;
                3'b101: coin_value = 500;
                default: coin_value = 0;
            endcase
        end
    endfunction

    // State register
    always @(posedge clk or posedge reset) begin
        if (reset)
            current_state <= IDLE;
        else
            current_state <= next_state;
    end

    // Output and balance logic
    always @(posedge clk or posedge reset) begin
        if (reset) begin
            product <= 0;
            refund_signal <= 0;
            change <= 0;
            balance <= 0;
        end else begin
            product <= 0;
            refund_signal <= 0;
            change <= 0;

            case (current_state)
                IDLE: begin
                    if (coin != 3'b000)
                        balance <= coin_value(coin);
                end

                COLLECT: begin
                    if (coin != 3'b000)
                        balance <= balance + coin_value(coin);
                end

                DISPENSE: begin
                    if (mode_select == 1) begin  // Auto Mode
                        if (balance >= 100) begin
                            product <= 1;
                            balance <= balance - 100;
                        end else begin
                            change <= balance;
                            balance <= 0;
                        end
                    end else begin  // Manual Mode
                        if (balance >= 100) begin
                            product <= 1;
                            balance <= balance - 100;
                        end
                    end
                end

                REFUND: begin
                    refund_signal <= 1;
                    change <= balance;
                    balance <= 0;
                end
            endcase
        end
    end

    // Next state logic
    always @(*) begin
        case (current_state)
            IDLE:
                next_state = (coin != 3'b000) ? COLLECT : IDLE;

            COLLECT:
                if (refund)
                    next_state = REFUND;
                else if (buy && balance >= 100)
                    next_state = DISPENSE;
                else
                    next_state = COLLECT;

            DISPENSE:
                if (mode_select == 1)  // Auto mode: loop dispensing
                    next_state = (balance >= 100) ? DISPENSE : IDLE;
                else                  // Manual mode: single dispense
                    next_state = IDLE;

            REFUND:
                next_state = IDLE;

            default:
                next_state = IDLE;
        endcase
    end

endmodule

VendingMachine_TB.v
`timescale 1ns / 1ps

module tb_vending_machine_dual_mode;

  reg clk, reset;
  reg [2:0] coin;
  reg buy, refund, mode_select;
  wire product, refund_signal;
  wire [15:0] balance, change;

  // DUT Instance
  vending_machine_dual_mode uut (
    .clk(clk),
    .reset(reset),
    .coin(coin),
    .buy(buy),
    .refund(refund),
    .mode_select(mode_select),
    .product(product),
    .refund_signal(refund_signal),
    .balance(balance),
    .change(change)
  );

  // Clock generation: 10ns period
  always #5 clk = ~clk;

  initial begin
    $dumpfile("vending_machine_dual_mode.vcd");
    $dumpvars(0, tb_vending_machine_dual_mode);

    // Initial state
    clk = 0; reset = 1;
    coin = 3'b000;
    buy = 0;
    refund = 0;
    mode_select = 0;

    #10 reset = 0;

    // === Test Case 1: Manual Mode ===
    $display("Manual Mode: Insert ₹500, Buy once");
    mode_select = 0;

    // Insert ₹500
    #10 coin = 3'b101; // ₹500
    #10 coin = 3'b000;

    // Press Buy
    #10 buy = 1;
    #10 buy = 0;

    // Press Buy again
    #20 buy = 1;
    #10 buy = 0;

    // Press Buy third time
    #20 buy = 1;
    #10 buy = 0;

    // Refund remaining balance
    #20 refund = 1;
    #10 refund = 0;

    // === Test Case 2: Auto Mode ===
    $display("Auto Mode: Insert ₹270, Buy");
    mode_select = 1;

    // Insert ₹100
    #20 coin = 3'b100; // ₹100
    #10 coin = 3'b000;

    // Insert ₹100
    #10 coin = 3'b100; // ₹100
    #10 coin = 3'b000;

    // Insert ₹50
    #10 coin = 3'b011; // ₹50
    #10 coin = 3'b000;

    // Insert ₹20 (simulate invalid coin input)
    #10 coin = 3'b110; // Invalid
    #10 coin = 3'b000;

    // Insert ₹20 as two ₹10 coins
    #10 coin = 3'b010;
    #10 coin = 3'b010;
    #10 coin = 3'b000;

    // Press Buy in auto mode
    #20 buy = 1;
    #10 buy = 0;

    #50 $finish;
  end

endmodule

vending_machine_dual_mode.vcd
$date
	Wed Jul 16 11:17:21 2025
$end
$version
	Icarus Verilog
$end
$timescale
	1ps
$end
$scope module tb_vending_machine_dual_mode $end
$var wire 1 ! refund_signal $end
$var wire 1 " product $end
$var wire 16 # change [15:0] $end
$var wire 16 $ balance [15:0] $end
$var reg 1 % buy $end
$var reg 1 & clk $end
$var reg 3 ' coin [2:0] $end
$var reg 1 ( mode_select $end
$var reg 1 ) refund $end
$var reg 1 * reset $end
$scope module uut $end
$var wire 1 % buy $end
$var wire 1 & clk $end
$var wire 3 + coin [2:0] $end
$var wire 1 ( mode_select $end
$var wire 1 ) refund $end
$var wire 1 * reset $end
$var parameter 2 , COLLECT $end
$var parameter 2 - DISPENSE $end
$var parameter 2 . IDLE $end
$var parameter 2 / REFUND $end
$var reg 16 0 balance [15:0] $end
$var reg 16 1 change [15:0] $end
$var reg 2 2 current_state [1:0] $end
$var reg 2 3 next_state [1:0] $end
$var reg 1 " product $end
$var reg 1 ! refund_signal $end
$scope function coin_value $end
$var reg 3 4 c [2:0] $end
$upscope $end
$upscope $end
$upscope $end
$enddefinitions $end
$comment Show the parameter values. $end
$dumpall
b11 /
b0 .
b10 -
b1 ,
$end
#0
$dumpvars
bx 4
b0 3
b0 2
b0 1
b0 0
b0 +
1*
0)
0(
b0 '
0&
0%
b0 $
b0 #
0"
0!
$end
#5000
1&
#10000
0&
0*
#15000
1&
#20000
b1 3
0&
b101 '
b101 +
#25000
b111110100 $
b111110100 0
b1 2
b101 4
1&
#30000
0&
b0 '
b0 +
#35000
1&
#40000
b10 3
0&
1%
#45000
b0 3
b10 2
1&
#50000
0&
0%
#55000
b0 2
b110010000 $
b110010000 0
1"
1&
#60000
0&
#65000
0"
1&
#70000
0&
1%
#75000
1&
#80000
0&
0%
#85000
1&
#90000
0&
#95000
1&
#100000
0&
1%
#105000
1&
#110000
0&
0%
#115000
1&
#120000
0&
#125000
1&
#130000
0&
1)
#135000
1&
#140000
0&
1(
0)
#145000
1&
#150000
0&
#155000
1&
#160000
b1 3
0&
b100 '
b100 +
#165000
b1100100 $
b1100100 0
b1 2
b100 4
1&
#170000
0&
b0 '
b0 +
#175000
1&
#180000
0&
b100 '
b100 +
#185000
b11001000 $
b11001000 0
1&
#190000
0&
b0 '
b0 +
#195000
1&
#200000
0&
b11 '
b11 +
#205000
b11111010 $
b11111010 0
b11 4
1&
#210000
0&
b0 '
b0 +
#215000
1&
#220000
0&
b110 '
b110 +
#225000
b110 4
1&
#230000
0&
b0 '
b0 +
#235000
1&
#240000
0&
b10 '
b10 +
#245000
b100000100 $
b100000100 0
b10 4
1&
#250000
0&
#255000
b100001110 $
b100001110 0
1&
#260000
0&
b0 '
b0 +
#265000
1&
#270000
0&
#275000
1&
#280000
b10 3
0&
1%
#285000
b10 2
1&
#290000
0&
0%
#295000
b10101010 $
b10101010 0
1"
1&
#300000
0&
#305000
b0 3
b1000110 $
b1000110 0
1"
1&
#310000
0&
#315000
b0 2
b0 $
b0 0
b1000110 #
b1000110 1
0"
1&
#320000
0&
#325000
b0 #
b0 1
1&
